odoo/addons/sale_order_line_effective_date/README.rst
odoo/addons/sale_order_line_effective_date/__init__.py
odoo/addons/sale_order_line_effective_date/__manifest__.py
odoo/addons/sale_order_line_effective_date/i18n/es.po
odoo/addons/sale_order_line_effective_date/i18n/it.po
odoo/addons/sale_order_line_effective_date/i18n/sale_order_line_effective_date.pot
odoo/addons/sale_order_line_effective_date/models/__init__.py
odoo/addons/sale_order_line_effective_date/models/sale_order_line.py
odoo/addons/sale_order_line_effective_date/readme/CONTRIBUTORS.md
odoo/addons/sale_order_line_effective_date/readme/DESCRIPTION.md
odoo/addons/sale_order_line_effective_date/readme/INSTALL.md
odoo/addons/sale_order_line_effective_date/readme/USAGE.md
odoo/addons/sale_order_line_effective_date/static/description/icon.png
odoo/addons/sale_order_line_effective_date/static/description/index.html
odoo/addons/sale_order_line_effective_date/tests/__init__.py
odoo/addons/sale_order_line_effective_date/tests/test_sale_order_line_effective_dates.py
odoo/addons/sale_order_line_effective_date/views/sale_order_line.xml
odoo_addon_sale_order_line_effective_date-16.0.1.1.0.2.dist-info/METADATA
odoo_addon_sale_order_line_effective_date-16.0.1.1.0.2.dist-info/WHEEL
odoo_addon_sale_order_line_effective_date-16.0.1.1.0.2.dist-info/top_level.txt
odoo_addon_sale_order_line_effective_date-16.0.1.1.0.2.dist-info/RECORD
